Metadata-Version: 2.4
Name: adventure-x-shitventure
Version: 0.114.514
Summary: 一个幽默的Python包，专注于排便补贴管理，纪念AdventureX 2025黑客松史上最传奇的厕所事件
Home-page: https://github.com/yourusername/adventure-x-shit
Author: Heijianserika
Author-email: your.email@example.com
Keywords: shit,subsidy,adventure,hackathon,toilet,humor
Classifier: Programming Language :: Python :: 3
Classifier: License :: OSI Approved :: MIT License
Classifier: Operating System :: OS Independent
Classifier: Topic :: Office/Business :: Financial
Classifier: Topic :: Utilities
Classifier: Development Status :: 4 - Beta
Classifier: Intended Audience :: Developers
Classifier: Intended Audience :: End Users/Desktop
Classifier: Natural Language :: Chinese (Simplified)
Requires-Python: >=3.7
License-File: LICENSE
Dynamic: author
Dynamic: author-email
Dynamic: classifier
Dynamic: description
Dynamic: description-content-type
Dynamic: home-page
Dynamic: keywords
Dynamic: license-file
Dynamic: requires-python
Dynamic: summary
